{
  "week": "2026-03-22",
  "report_period": {
    "start": "2026-03-15",
    "end": "2026-03-21"
  },
  "version": "Weekly Vol.2026-03-22-R2",
  "generated_at": "2026-03-21T20:54:26.609Z",
  "metrics": {
    "covered_countries": 16,
    "lg_promotion_signals": 350,
    "competitor_promotion_signals": 12,
    "chinese_threat_signals": 14,
    "consumer_negative_countries": 53,
    "critical_country_count": 4
  },
  "critical_countries": [
    "🇩🇪 독일 (DE)",
    "🇮🇹 이탈리아 (IT)",
    "🇦🇺 호주 (AU)",
    "🇹🇷 튀르키예 (TR)"
  ],
  "executive_key_insights": [
    "**LG InnoFest 2026 브라질 개최**: LG의 AI 기반 스마트홈 비전이 글로벌 언론에 집중 조명되며, 특히 InstaView 냉장고와 WashCombo 세탁기의 에너지 절감 기능이 남미 시장에서 브랜드 프리미엄 포지셔닝을 강화하고 있음",
    "**중국 브랜드 전방위 공세**: TCL의 MicroLED TV 가격 파괴($36,500 163인치)와 Haier의 유럽 냉장고·세탁기 시장 리더십 도전이 동시 진행되며, TV뿐 아니라 생활가전 전반에서 위협 수위가 상승",
    "**LG UltraFine evo 6K 모니터 출시**: 전 세계 최초 6K Thunderbolt 5 모니터로 크리에이터 시장 공략이 본격화되며, 대만을 필두로 아시아 프리미엄 시장에서 차별화된 포지셔닝 확보"
  ],
  "links": {
    "html": "./2026-03-22/index.html",
    "pdf": "../pdf/LG_Global_D2C_Weekly_Intelligence_2026-03-22_R2_16country.pdf",
    "md": "../md/LG_Global_D2C_Weekly_Intelligence_2026-03-22_R2_16country.md",
    "share": "./2026-03-22/share.html"
  }
}
