{
  "week": "2026-03-08",
  "report_period": {
    "start": "2026-03-01",
    "end": "2026-03-07"
  },
  "version": "Weekly Vol.2026-03-08-R2",
  "generated_at": "2026-03-08T07:44:25.338Z",
  "metrics": {
    "covered_countries": 14,
    "lg_promotion_signals": 309,
    "competitor_promotion_signals": 6,
    "chinese_threat_signals": 12,
    "consumer_negative_countries": 0,
    "critical_country_count": 3
  },
  "critical_countries": [
    "🇺🇸 미국 (US)",
    "🇦🇺 호주 (AU)",
    "🇸🇦 사우디아라비아 (SA)"
  ],
  "executive_key_insights": [
    "**LG OLED C6/G6 2026년 신제품 글로벌 사전예약 개시**: 미국/유럽 전역에서 C6 $1,399~, G6 $2,199~ 가격 공개로 전작 대비 가격 동결 및 일부 하락세 확인, 프리미엄 TV 시장 주도권 유지 전략 가시화",
    "**중국 브랜드 전방위 공세 심화**: TV(TCL 1,040Hz 모니터, Hisense 100인치 $1,400 공격가)와 가전(Midea/Haier 브라질·호주 확장) 동시 위협으로 중저가 세그먼트 압박 가중",
    "**생활가전 A/S 불만 신호 감지**: 브라질 Midea 세탁기 고장 불만 급증(Reclame AQUI 9건+), 영국/미국 LG 세탁기 디스펜서 잔수 이슈 등 품질 경험 개선 필요"
  ],
  "links": {
    "html": "./2026-03-08/index.html",
    "pdf": "../pdf/LG_Global_D2C_Weekly_Intelligence_2026-03-08_R2_16country.pdf",
    "md": "../md/LG_Global_D2C_Weekly_Intelligence_2026-03-08_R2_16country.md",
    "share": "./2026-03-08/share.html"
  }
}
